{
    "directed": false,
    "multigraph": false,
    "graph": [],
    "nodes": [
        {
            "TOTPOP": 1,
            "x": 0,
            "y": 0,
            "county": "1",
            "district": "1",
            "precinct": 0,
            "muni": "1",
            "boundary_node": true,
            "boundary_perim": 1,
            "water_dist": "2",
            "WVAP": 0.8999532942809672,
            "POCVAP": 0.10004670571903285,
            "dem_percent": 0.4409831573065591,
            "rep_percent": 0.5590168426934409,
            "id": 0
        },
        {
            "TOTPOP": 1,
            "x": 0,
            "y": 1,
            "county": "1",
            "district": "1",
            "precinct": 1,
            "muni": "1",
            "boundary_node": true,
            "boundary_perim": 1,
            "water_dist": "2",
            "WVAP": 0.6952197298890357,
            "POCVAP": 0.3047802701109643,
            "dem_percent": 0.5652242506411572,
            "rep_percent": 0.4347757493588428,
            "id": 1
        },
        {
            "TOTPOP": 1,
            "x": 0,
            "y": 2,
            "county": "1",
            "district": "1",
            "precinct": 2,
            "muni": "5",
            "boundary_node": true,
            "boundary_perim": 1,
            "water_dist": "2",
            "WVAP": 0.6491160008911517,
            "POCVAP": 0.35088399910884827,
            "dem_percent": 0.6038524344445779,
            "rep_percent": 0.3961475655554221,
            "id": 2
        },
        {
            "TOTPOP": 1,
            "x": 0,
            "y": 3,
            "county": "1",
            "district": "1",
            "precinct": 3,
            "muni": "5",
            "boundary_node": true,
            "boundary_perim": 1,
            "water_dist": "2",
            "WVAP": 0.8287910974784788,
            "POCVAP": 0.1712089025215212,
            "dem_percent": 0.5445619583377953,
            "rep_percent": 0.4554380416622047,
            "id": 3
        },
        {
            "TOTPOP": 1,
            "x": 0,
            "y": 4,
            "county": "3",
            "district": "1",
            "precinct": 4,
            "muni": "9",
            "boundary_node": true,
            "boundary_perim": 1,
            "water_dist": "2",
            "WVAP": 0.6448261185188695,
            "POCVAP": 0.3551738814811305,
            "dem_percent": 0.6003300582985407,
            "rep_percent": 0.3996699417014593,
            "id": 4
        },
        {
            "TOTPOP": 1,
            "x": 0,
            "y": 5,
            "county": "3",
            "district": "1",
            "precinct": 5,
            "muni": "9",
            "boundary_node": true,
            "boundary_perim": 1,
            "water_dist": "2",
            "WVAP": 0.7324539449974946,
            "POCVAP": 0.2675460550025054,
            "dem_percent": 0.5737899664620787,
            "rep_percent": 0.4262100335379213,
            "id": 5
        },
        {
            "TOTPOP": 1,
            "x": 0,
            "y": 6,
            "county": "3",
            "district": "1",
            "precinct": 6,
            "muni": "13",
            "boundary_node": true,
            "boundary_perim": 1,
            "water_dist": "2",
            "WVAP": 0.694001903939866,
            "POCVAP": 0.30599809606013395,
            "dem_percent": 0.5015871146077282,
            "rep_percent": 0.4984128853922718,
            "id": 6
        },
        {
            "TOTPOP": 1,
            "x": 0,
            "y": 7,
            "county": "3",
            "district": "1",
            "precinct": 7,
            "muni": "13",
            "boundary_node": true,
            "boundary_perim": 1,
            "water_dist": "2",
            "WVAP": 0.6661827724034276,
            "POCVAP": 0.3338172275965724,
            "dem_percent": 0.5091975963577065,
            "rep_percent": 0.49080240364229355,
            "id": 7
        },
        {
            "TOTPOP": 1,
            "x": 1,
            "y": 0,
            "county": "1",
            "district": "2",
            "precinct": 8,
            "muni": "1",
            "boundary_node": true,
            "boundary_perim": 1,
            "water_dist": "2",
            "WVAP": 0.7823006829840382,
            "POCVAP": 0.2176993170159618,
            "dem_percent": 0.5062447618959101,
            "rep_percent": 0.49375523810408994,
            "id": 8
        },
        {
            "TOTPOP": 1,
            "x": 1,
            "y": 1,
            "county": "1",
            "district": "2",
            "precinct": 9,
            "muni": "1",
            "boundary_node": false,
            "boundary_perim": 0,
            "water_dist": "2",
            "WVAP": 0.6799450418968433,
            "POCVAP": 0.32005495810315665,
            "dem_percent": 0.49733035181838825,
            "rep_percent": 0.5026696481816118,
            "id": 9
        },
        {
            "TOTPOP": 1,
            "x": 1,
            "y": 2,
            "county": "1",
            "district": "2",
            "precinct": 10,
            "muni": "5",
            "boundary_node": false,
            "boundary_perim": 0,
            "water_dist": "2",
            "WVAP": 0.6953268849850948,
            "POCVAP": 0.30467311501490524,
            "dem_percent": 0.5589469793631627,
            "rep_percent": 0.44105302063683727,
            "id": 10
        },
        {
            "TOTPOP": 1,
            "x": 1,
            "y": 3,
            "county": "1",
            "district": "2",
            "precinct": 11,
            "muni": "5",
            "boundary_node": false,
            "boundary_perim": 0,
            "water_dist": "2",
            "WVAP": 0.6673757614387511,
            "POCVAP": 0.3326242385612489,
            "dem_percent": 0.4827218627234941,
            "rep_percent": 0.5172781372765058,
            "id": 11
        },
        {
            "TOTPOP": 1,
            "x": 1,
            "y": 4,
            "county": "3",
            "district": "2",
            "precinct": 12,
            "muni": "9",
            "boundary_node": false,
            "boundary_perim": 0,
            "water_dist": "2",
            "WVAP": 0.8447878871087493,
            "POCVAP": 0.1552121128912507,
            "dem_percent": 0.464726961614725,
            "rep_percent": 0.5352730383852751,
            "id": 12
        },
        {
            "TOTPOP": 1,
            "x": 1,
            "y": 5,
            "county": "3",
            "district": "2",
            "precinct": 13,
            "muni": "9",
            "boundary_node": false,
            "boundary_perim": 0,
            "water_dist": "2",
            "WVAP": 0.7955058602087937,
            "POCVAP": 0.20449413979120634,
            "dem_percent": 0.48187602016687625,
            "rep_percent": 0.5181239798331237,
            "id": 13
        },
        {
            "TOTPOP": 1,
            "x": 1,
            "y": 6,
            "county": "3",
            "district": "2",
            "precinct": 14,
            "muni": "13",
            "boundary_node": false,
            "boundary_perim": 0,
            "water_dist": "4",
            "WVAP": 0.6871289576387627,
            "POCVAP": 0.3128710423612373,
            "dem_percent": 0.5242632411468189,
            "rep_percent": 0.4757367588531811,
            "id": 14
        },
        {
            "TOTPOP": 1,
            "x": 1,
            "y": 7,
            "county": "3",
            "district": "2",
            "precinct": 15,
            "muni": "13",
            "boundary_node": true,
            "boundary_perim": 1,
            "water_dist": "4",
            "WVAP": 0.6965590695054472,
            "POCVAP": 0.3034409304945528,
            "dem_percent": 0.4735657100620079,
            "rep_percent": 0.5264342899379921,
            "id": 15
        },
        {
            "TOTPOP": 1,
            "x": 2,
            "y": 0,
            "county": "1",
            "district": "3",
            "precinct": 16,
            "muni": "2",
            "boundary_node": true,
            "boundary_perim": 1,
            "water_dist": "4",
            "WVAP": 0.7046183164142773,
            "POCVAP": 0.2953816835857227,
            "dem_percent": 0.5099718281264534,
            "rep_percent": 0.49002817187354664,
            "id": 16
        },
        {
            "TOTPOP": 1,
            "x": 2,
            "y": 1,
            "county": "1",
            "district": "3",
            "precinct": 17,
            "muni": "2",
            "boundary_node": false,
            "boundary_perim": 0,
            "water_dist": "4",
            "WVAP": 0.774328092965314,
            "POCVAP": 0.22567190703468598,
            "dem_percent": 0.45286939847544927,
            "rep_percent": 0.5471306015245507,
            "id": 17
        },
        {
            "TOTPOP": 1,
            "x": 2,
            "y": 2,
            "county": "1",
            "district": "3",
            "precinct": 18,
            "muni": "6",
            "boundary_node": false,
            "boundary_perim": 0,
            "water_dist": "2",
            "WVAP": 0.8959344661693388,
            "POCVAP": 0.1040655338306612,
            "dem_percent": 0.47549165771857865,
            "rep_percent": 0.5245083422814214,
            "id": 18
        },
        {
            "TOTPOP": 1,
            "x": 2,
            "y": 3,
            "county": "1",
            "district": "3",
            "precinct": 19,
            "muni": "6",
            "boundary_node": false,
            "boundary_perim": 0,
            "water_dist": "2",
            "WVAP": 0.7045502613926866,
            "POCVAP": 0.2954497386073134,
            "dem_percent": 0.5558443821305725,
            "rep_percent": 0.4441556178694275,
            "id": 19
        },
        {
            "TOTPOP": 1,
            "x": 2,
            "y": 4,
            "county": "3",
            "district": "3",
            "precinct": 20,
            "muni": "10",
            "boundary_node": false,
            "boundary_perim": 0,
            "water_dist": "4",
            "WVAP": 0.7801140185710627,
            "POCVAP": 0.21988598142893734,
            "dem_percent": 0.4766206368548507,
            "rep_percent": 0.5233793631451493,
            "id": 20
        },
        {
            "TOTPOP": 1,
            "x": 2,
            "y": 5,
            "county": "3",
            "district": "3",
            "precinct": 21,
            "muni": "10",
            "boundary_node": false,
            "boundary_perim": 0,
            "water_dist": "4",
            "WVAP": 0.6260032060156777,
            "POCVAP": 0.3739967939843223,
            "dem_percent": 0.5401186319017088,
            "rep_percent": 0.45988136809829117,
            "id": 21
        },
        {
            "TOTPOP": 1,
            "x": 2,
            "y": 6,
            "county": "3",
            "district": "3",
            "precinct": 22,
            "muni": "14",
            "boundary_node": false,
            "boundary_perim": 0,
            "water_dist": "4",
            "WVAP": 0.7517000114176184,
            "POCVAP": 0.24829998858238156,
            "dem_percent": 0.4420443355940721,
            "rep_percent": 0.5579556644059279,
            "id": 22
        },
        {
            "TOTPOP": 1,
            "x": 2,
            "y": 7,
            "county": "3",
            "district": "3",
            "precinct": 23,
            "muni": "14",
            "boundary_node": true,
            "boundary_perim": 1,
            "water_dist": "4",
            "WVAP": 0.6347924869178856,
            "POCVAP": 0.3652075130821144,
            "dem_percent": 0.5965096594787689,
            "rep_percent": 0.4034903405212311,
            "id": 23
        },
        {
            "TOTPOP": 1,
            "x": 3,
            "y": 0,
            "county": "1",
            "district": "4",
            "precinct": 24,
            "muni": "2",
            "boundary_node": true,
            "boundary_perim": 1,
            "water_dist": "4",
            "WVAP": 0.7267903168143979,
            "POCVAP": 0.2732096831856021,
            "dem_percent": 0.5812813161314889,
            "rep_percent": 0.4187186838685111,
            "id": 24
        },
        {
            "TOTPOP": 1,
            "x": 3,
            "y": 1,
            "county": "1",
            "district": "4",
            "precinct": 25,
            "muni": "2",
            "boundary_node": false,
            "boundary_perim": 0,
            "water_dist": "4",
            "WVAP": 0.6721369576577855,
            "POCVAP": 0.32786304234221453,
            "dem_percent": 0.5522501383261251,
            "rep_percent": 0.44774986167387487,
            "id": 25
        },
        {
            "TOTPOP": 1,
            "x": 3,
            "y": 2,
            "county": "1",
            "district": "4",
            "precinct": 26,
            "muni": "6",
            "boundary_node": false,
            "boundary_perim": 0,
            "water_dist": "4",
            "WVAP": 0.8104286254440287,
            "POCVAP": 0.18957137455597128,
            "dem_percent": 0.5464795424955267,
            "rep_percent": 0.45352045750447334,
            "id": 26
        },
        {
            "TOTPOP": 1,
            "x": 3,
            "y": 3,
            "county": "1",
            "district": "4",
            "precinct": 27,
            "muni": "6",
            "boundary_node": false,
            "boundary_perim": 0,
            "water_dist": "4",
            "WVAP": 0.8702955772119703,
            "POCVAP": 0.12970442278802974,
            "dem_percent": 0.4279399164237119,
            "rep_percent": 0.5720600835762881,
            "id": 27
        },
        {
            "TOTPOP": 1,
            "x": 3,
            "y": 4,
            "county": "3",
            "district": "4",
            "precinct": 28,
            "muni": "10",
            "boundary_node": false,
            "boundary_perim": 0,
            "water_dist": "4",
            "WVAP": 0.6767975571686359,
            "POCVAP": 0.3232024428313641,
            "dem_percent": 0.4869511339856877,
            "rep_percent": 0.5130488660143123,
            "id": 28
        },
        {
            "TOTPOP": 1,
            "x": 3,
            "y": 5,
            "county": "3",
            "district": "4",
            "precinct": 29,
            "muni": "10",
            "boundary_node": false,
            "boundary_perim": 0,
            "water_dist": "1",
            "WVAP": 0.7001106373684809,
            "POCVAP": 0.2998893626315191,
            "dem_percent": 0.48899089055428874,
            "rep_percent": 0.5110091094457112,
            "id": 29
        },
        {
            "TOTPOP": 1,
            "x": 3,
            "y": 6,
            "county": "3",
            "district": "4",
            "precinct": 30,
            "muni": "14",
            "boundary_node": false,
            "boundary_perim": 0,
            "water_dist": "1",
            "WVAP": 0.8981448225753991,
            "POCVAP": 0.10185517742460093,
            "dem_percent": 0.4968726225395352,
            "rep_percent": 0.5031273774604648,
            "id": 30
        },
        {
            "TOTPOP": 1,
            "x": 3,
            "y": 7,
            "county": "3",
            "district": "4",
            "precinct": 31,
            "muni": "14",
            "boundary_node": true,
            "boundary_perim": 1,
            "water_dist": "1",
            "WVAP": 0.8953067894675182,
            "POCVAP": 0.10469321053248182,
            "dem_percent": 0.4335300525811208,
            "rep_percent": 0.5664699474188792,
            "id": 31
        },
        {
            "TOTPOP": 1,
            "x": 4,
            "y": 0,
            "county": "2",
            "district": "5",
            "precinct": 32,
            "muni": "3",
            "boundary_node": true,
            "boundary_perim": 1,
            "water_dist": "3",
            "WVAP": 0.7742228892651848,
            "POCVAP": 0.2257771107348152,
            "dem_percent": 0.4316484441052302,
            "rep_percent": 0.5683515558947698,
            "id": 32
        },
        {
            "TOTPOP": 1,
            "x": 4,
            "y": 1,
            "county": "2",
            "district": "5",
            "precinct": 33,
            "muni": "3",
            "boundary_node": false,
            "boundary_perim": 0,
            "water_dist": "3",
            "WVAP": 0.6620975313192276,
            "POCVAP": 0.33790246868077245,
            "dem_percent": 0.5775420087151975,
            "rep_percent": 0.42245799128480255,
            "id": 33
        },
        {
            "TOTPOP": 1,
            "x": 4,
            "y": 2,
            "county": "2",
            "district": "5",
            "precinct": 34,
            "muni": "7",
            "boundary_node": false,
            "boundary_perim": 0,
            "water_dist": "3",
            "WVAP": 0.6584708684122075,
            "POCVAP": 0.3415291315877925,
            "dem_percent": 0.590875567350819,
            "rep_percent": 0.40912443264918097,
            "id": 34
        },
        {
            "TOTPOP": 1,
            "x": 4,
            "y": 3,
            "county": "2",
            "district": "5",
            "precinct": 35,
            "muni": "7",
            "boundary_node": false,
            "boundary_perim": 0,
            "water_dist": "4",
            "WVAP": 0.8842788331256952,
            "POCVAP": 0.11572116687430478,
            "dem_percent": 0.43717280382869694,
            "rep_percent": 0.5628271961713031,
            "id": 35
        },
        {
            "TOTPOP": 1,
            "x": 4,
            "y": 4,
            "county": "4",
            "district": "5",
            "precinct": 36,
            "muni": "11",
            "boundary_node": false,
            "boundary_perim": 0,
            "water_dist": "4",
            "WVAP": 0.6779606212622615,
            "POCVAP": 0.32203937873773847,
            "dem_percent": 0.5064705163745823,
            "rep_percent": 0.4935294836254177,
            "id": 36
        },
        {
            "TOTPOP": 1,
            "x": 4,
            "y": 5,
            "county": "4",
            "district": "5",
            "precinct": 37,
            "muni": "11",
            "boundary_node": false,
            "boundary_perim": 0,
            "water_dist": "1",
            "WVAP": 0.7517481922415834,
            "POCVAP": 0.2482518077584166,
            "dem_percent": 0.4690906133431705,
            "rep_percent": 0.5309093866568295,
            "id": 37
        },
        {
            "TOTPOP": 1,
            "x": 4,
            "y": 6,
            "county": "4",
            "district": "5",
            "precinct": 38,
            "muni": "15",
            "boundary_node": false,
            "boundary_perim": 0,
            "water_dist": "1",
            "WVAP": 0.8182223704623903,
            "POCVAP": 0.18177762953760968,
            "dem_percent": 0.5476548733772322,
            "rep_percent": 0.4523451266227678,
            "id": 38
        },
        {
            "TOTPOP": 1,
            "x": 4,
            "y": 7,
            "county": "4",
            "district": "5",
            "precinct": 39,
            "muni": "15",
            "boundary_node": true,
            "boundary_perim": 1,
            "water_dist": "1",
            "WVAP": 0.8034002556947166,
            "POCVAP": 0.19659974430528337,
            "dem_percent": 0.4484750774880886,
            "rep_percent": 0.5515249225119114,
            "id": 39
        },
        {
            "TOTPOP": 1,
            "x": 5,
            "y": 0,
            "county": "2",
            "district": "6",
            "precinct": 40,
            "muni": "3",
            "boundary_node": true,
            "boundary_perim": 1,
            "water_dist": "3",
            "WVAP": 0.6565210457555012,
            "POCVAP": 0.3434789542444988,
            "dem_percent": 0.5247947770577597,
            "rep_percent": 0.4752052229422403,
            "id": 40
        },
        {
            "TOTPOP": 1,
            "x": 5,
            "y": 1,
            "county": "2",
            "district": "6",
            "precinct": 41,
            "muni": "3",
            "boundary_node": false,
            "boundary_perim": 0,
            "water_dist": "3",
            "WVAP": 0.6034430234551327,
            "POCVAP": 0.3965569765448673,
            "dem_percent": 0.615022573621989,
            "rep_percent": 0.384977426378011,
            "id": 41
        },
        {
            "TOTPOP": 1,
            "x": 5,
            "y": 2,
            "county": "2",
            "district": "6",
            "precinct": 42,
            "muni": "7",
            "boundary_node": false,
            "boundary_perim": 0,
            "water_dist": "3",
            "WVAP": 0.6707893272585074,
            "POCVAP": 0.3292106727414926,
            "dem_percent": 0.5559371438964333,
            "rep_percent": 0.44406285610356666,
            "id": 42
        },
        {
            "TOTPOP": 1,
            "x": 5,
            "y": 3,
            "county": "2",
            "district": "6",
            "precinct": 43,
            "muni": "7",
            "boundary_node": false,
            "boundary_perim": 0,
            "water_dist": "4",
            "WVAP": 0.6886883688976551,
            "POCVAP": 0.31131163110234494,
            "dem_percent": 0.4890970447755878,
            "rep_percent": 0.5109029552244122,
            "id": 43
        },
        {
            "TOTPOP": 1,
            "x": 5,
            "y": 4,
            "county": "4",
            "district": "6",
            "precinct": 44,
            "muni": "11",
            "boundary_node": false,
            "boundary_perim": 0,
            "water_dist": "1",
            "WVAP": 0.8279839172861666,
            "POCVAP": 0.1720160827138334,
            "dem_percent": 0.4066512957918783,
            "rep_percent": 0.5933487042081217,
            "id": 44
        },
        {
            "TOTPOP": 1,
            "x": 5,
            "y": 5,
            "county": "4",
            "district": "6",
            "precinct": 45,
            "muni": "11",
            "boundary_node": false,
            "boundary_perim": 0,
            "water_dist": "1",
            "WVAP": 0.6950425678651451,
            "POCVAP": 0.30495743213485493,
            "dem_percent": 0.5871910086126438,
            "rep_percent": 0.41280899138735616,
            "id": 45
        },
        {
            "TOTPOP": 1,
            "x": 5,
            "y": 6,
            "county": "4",
            "district": "6",
            "precinct": 46,
            "muni": "15",
            "boundary_node": false,
            "boundary_perim": 0,
            "water_dist": "1",
            "WVAP": 0.7775499163565247,
            "POCVAP": 0.2224500836434753,
            "dem_percent": 0.4381366895987993,
            "rep_percent": 0.5618633104012007,
            "id": 46
        },
        {
            "TOTPOP": 1,
            "x": 5,
            "y": 7,
            "county": "4",
            "district": "6",
            "precinct": 47,
            "muni": "15",
            "boundary_node": true,
            "boundary_perim": 1,
            "water_dist": "1",
            "WVAP": 0.8168073856241902,
            "POCVAP": 0.1831926143758098,
            "dem_percent": 0.5341515974955332,
            "rep_percent": 0.4658484025044668,
            "id": 47
        },
        {
            "TOTPOP": 1,
            "x": 6,
            "y": 0,
            "county": "2",
            "district": "7",
            "precinct": 48,
            "muni": "4",
            "boundary_node": true,
            "boundary_perim": 1,
            "water_dist": "3",
            "WVAP": 0.864878645233728,
            "POCVAP": 0.13512135476627196,
            "dem_percent": 0.3930473303067467,
            "rep_percent": 0.6069526696932532,
            "id": 48
        },
        {
            "TOTPOP": 1,
            "x": 6,
            "y": 1,
            "county": "2",
            "district": "7",
            "precinct": 49,
            "muni": "4",
            "boundary_node": false,
            "boundary_perim": 0,
            "water_dist": "3",
            "WVAP": 0.681693923274576,
            "POCVAP": 0.318306076725424,
            "dem_percent": 0.47327925592546194,
            "rep_percent": 0.5267207440745381,
            "id": 49
        },
        {
            "TOTPOP": 1,
            "x": 6,
            "y": 2,
            "county": "2",
            "district": "7",
            "precinct": 50,
            "muni": "8",
            "boundary_node": false,
            "boundary_perim": 0,
            "water_dist": "3",
            "WVAP": 0.6959656798946109,
            "POCVAP": 0.3040343201053891,
            "dem_percent": 0.5098669807511037,
            "rep_percent": 0.4901330192488963,
            "id": 50
        },
        {
            "TOTPOP": 1,
            "x": 6,
            "y": 3,
            "county": "2",
            "district": "7",
            "precinct": 51,
            "muni": "8",
            "boundary_node": false,
            "boundary_perim": 0,
            "water_dist": "3",
            "WVAP": 0.7084036752086827,
            "POCVAP": 0.29159632479131725,
            "dem_percent": 0.4924232590812946,
            "rep_percent": 0.5075767409187054,
            "id": 51
        },
        {
            "TOTPOP": 1,
            "x": 6,
            "y": 4,
            "county": "4",
            "district": "7",
            "precinct": 52,
            "muni": "12",
            "boundary_node": false,
            "boundary_perim": 0,
            "water_dist": "3",
            "WVAP": 0.8915466033470476,
            "POCVAP": 0.1084533966529524,
            "dem_percent": 0.4942663621658382,
            "rep_percent": 0.5057336378341618,
            "id": 52
        },
        {
            "TOTPOP": 1,
            "x": 6,
            "y": 5,
            "county": "4",
            "district": "7",
            "precinct": 53,
            "muni": "12",
            "boundary_node": false,
            "boundary_perim": 0,
            "water_dist": "1",
            "WVAP": 0.7374639224144879,
            "POCVAP": 0.2625360775855121,
            "dem_percent": 0.4778174930138776,
            "rep_percent": 0.5221825069861223,
            "id": 53
        },
        {
            "TOTPOP": 1,
            "x": 6,
            "y": 6,
            "county": "4",
            "district": "7",
            "precinct": 54,
            "muni": "16",
            "boundary_node": false,
            "boundary_perim": 0,
            "water_dist": "1",
            "WVAP": 0.8039648920913283,
            "POCVAP": 0.19603510790867174,
            "dem_percent": 0.5579922254086028,
            "rep_percent": 0.4420077745913972,
            "id": 54
        },
        {
            "TOTPOP": 1,
            "x": 6,
            "y": 7,
            "county": "4",
            "district": "7",
            "precinct": 55,
            "muni": "16",
            "boundary_node": true,
            "boundary_perim": 1,
            "water_dist": "1",
            "WVAP": 0.8010351162525163,
            "POCVAP": 0.19896488374748367,
            "dem_percent": 0.45493957178978833,
            "rep_percent": 0.5450604282102116,
            "id": 55
        },
        {
            "TOTPOP": 1,
            "x": 7,
            "y": 0,
            "county": "2",
            "district": "8",
            "precinct": 56,
            "muni": "4",
            "boundary_node": true,
            "boundary_perim": 1,
            "water_dist": "3",
            "WVAP": 0.6013867713908647,
            "POCVAP": 0.3986132286091353,
            "dem_percent": 0.5669795758913598,
            "rep_percent": 0.43302042410864017,
            "id": 56
        },
        {
            "TOTPOP": 1,
            "x": 7,
            "y": 1,
            "county": "2",
            "district": "8",
            "precinct": 57,
            "muni": "4",
            "boundary_node": true,
            "boundary_perim": 1,
            "water_dist": "3",
            "WVAP": 0.8642858458726776,
            "POCVAP": 0.13571415412732235,
            "dem_percent": 0.42300781426195233,
            "rep_percent": 0.5769921857380477,
            "id": 57
        },
        {
            "TOTPOP": 1,
            "x": 7,
            "y": 2,
            "county": "2",
            "district": "8",
            "precinct": 58,
            "muni": "8",
            "boundary_node": true,
            "boundary_perim": 1,
            "water_dist": "3",
            "WVAP": 0.8343463001840107,
            "POCVAP": 0.16565369981598932,
            "dem_percent": 0.5385566333384654,
            "rep_percent": 0.4614433666615346,
            "id": 58
        },
        {
            "TOTPOP": 1,
            "x": 7,
            "y": 3,
            "county": "2",
            "district": "8",
            "precinct": 59,
            "muni": "8",
            "boundary_node": true,
            "boundary_perim": 1,
            "water_dist": "3",
            "WVAP": 0.8042355207023617,
            "POCVAP": 0.1957644792976383,
            "dem_percent": 0.5419769526474589,
            "rep_percent": 0.45802304735254107,
            "id": 59
        },
        {
            "TOTPOP": 1,
            "x": 7,
            "y": 4,
            "county": "4",
            "district": "8",
            "precinct": 60,
            "muni": "12",
            "boundary_node": true,
            "boundary_perim": 1,
            "water_dist": "3",
            "WVAP": 0.6310572979499521,
            "POCVAP": 0.36894270205004787,
            "dem_percent": 0.5346343257477048,
            "rep_percent": 0.46536567425229525,
            "id": 60
        },
        {
            "TOTPOP": 1,
            "x": 7,
            "y": 5,
            "county": "4",
            "district": "8",
            "precinct": 61,
            "muni": "12",
            "boundary_node": true,
            "boundary_perim": 1,
            "water_dist": "1",
            "WVAP": 0.8582768316641896,
            "POCVAP": 0.14172316833581045,
            "dem_percent": 0.48275738437589966,
            "rep_percent": 0.5172426156241003,
            "id": 61
        },
        {
            "TOTPOP": 1,
            "x": 7,
            "y": 6,
            "county": "4",
            "district": "8",
            "precinct": 62,
            "muni": "16",
            "boundary_node": true,
            "boundary_perim": 1,
            "water_dist": "1",
            "WVAP": 0.7206665690520977,
            "POCVAP": 0.2793334309479023,
            "dem_percent": 0.46760238711835567,
            "rep_percent": 0.5323976128816443,
            "id": 62
        },
        {
            "TOTPOP": 1,
            "x": 7,
            "y": 7,
            "county": "4",
            "district": "8",
            "precinct": 63,
            "muni": "16",
            "boundary_node": true,
            "boundary_perim": 1,
            "water_dist": "1",
            "WVAP": 0.8694655136846785,
            "POCVAP": 0.1305344863153215,
            "dem_percent": 0.5042548970982954,
            "rep_percent": 0.4957451029017046,
            "id": 63
        }
    ],
    "adjacency": [
        [{ "id": 8 }, { "id": 1 }],
        [{ "id": 0 }, { "id": 9 }, { "id": 2 }],
        [{ "id": 1 }, { "id": 10 }, { "id": 3 }],
        [{ "id": 2 }, { "id": 11 }, { "id": 4 }],
        [{ "id": 3 }, { "id": 12 }, { "id": 5 }],
        [{ "id": 4 }, { "id": 13 }, { "id": 6 }],
        [{ "id": 5 }, { "id": 14 }, { "id": 7 }],
        [{ "id": 6 }, { "id": 15 }],
        [{ "id": 0 }, { "id": 16 }, { "id": 9 }],
        [{ "id": 1 }, { "id": 8 }, { "id": 17 }, { "id": 10 }],
        [{ "id": 2 }, { "id": 9 }, { "id": 18 }, { "id": 11 }],
        [{ "id": 3 }, { "id": 10 }, { "id": 19 }, { "id": 12 }],
        [{ "id": 4 }, { "id": 11 }, { "id": 20 }, { "id": 13 }],
        [{ "id": 5 }, { "id": 12 }, { "id": 21 }, { "id": 14 }],
        [{ "id": 6 }, { "id": 13 }, { "id": 22 }, { "id": 15 }],
        [{ "id": 7 }, { "id": 14 }, { "id": 23 }],
        [{ "id": 8 }, { "id": 24 }, { "id": 17 }],
        [{ "id": 9 }, { "id": 16 }, { "id": 25 }, { "id": 18 }],
        [{ "id": 10 }, { "id": 17 }, { "id": 26 }, { "id": 19 }],
        [{ "id": 11 }, { "id": 18 }, { "id": 27 }, { "id": 20 }],
        [{ "id": 12 }, { "id": 19 }, { "id": 28 }, { "id": 21 }],
        [{ "id": 13 }, { "id": 20 }, { "id": 29 }, { "id": 22 }],
        [{ "id": 14 }, { "id": 21 }, { "id": 30 }, { "id": 23 }],
        [{ "id": 15 }, { "id": 22 }, { "id": 31 }],
        [{ "id": 16 }, { "id": 32 }, { "id": 25 }],
        [{ "id": 17 }, { "id": 24 }, { "id": 33 }, { "id": 26 }],
        [{ "id": 18 }, { "id": 25 }, { "id": 34 }, { "id": 27 }],
        [{ "id": 19 }, { "id": 26 }, { "id": 35 }, { "id": 28 }],
        [{ "id": 20 }, { "id": 27 }, { "id": 36 }, { "id": 29 }],
        [{ "id": 21 }, { "id": 28 }, { "id": 37 }, { "id": 30 }],
        [{ "id": 22 }, { "id": 29 }, { "id": 38 }, { "id": 31 }],
        [{ "id": 23 }, { "id": 30 }, { "id": 39 }],
        [{ "id": 24 }, { "id": 40 }, { "id": 33 }],
        [{ "id": 25 }, { "id": 32 }, { "id": 41 }, { "id": 34 }],
        [{ "id": 26 }, { "id": 33 }, { "id": 42 }, { "id": 35 }],
        [{ "id": 27 }, { "id": 34 }, { "id": 43 }, { "id": 36 }],
        [{ "id": 28 }, { "id": 35 }, { "id": 44 }, { "id": 37 }],
        [{ "id": 29 }, { "id": 36 }, { "id": 45 }, { "id": 38 }],
        [{ "id": 30 }, { "id": 37 }, { "id": 46 }, { "id": 39 }],
        [{ "id": 31 }, { "id": 38 }, { "id": 47 }],
        [{ "id": 32 }, { "id": 48 }, { "id": 41 }],
        [{ "id": 33 }, { "id": 40 }, { "id": 49 }, { "id": 42 }],
        [{ "id": 34 }, { "id": 41 }, { "id": 50 }, { "id": 43 }],
        [{ "id": 35 }, { "id": 42 }, { "id": 51 }, { "id": 44 }],
        [{ "id": 36 }, { "id": 43 }, { "id": 52 }, { "id": 45 }],
        [{ "id": 37 }, { "id": 44 }, { "id": 53 }, { "id": 46 }],
        [{ "id": 38 }, { "id": 45 }, { "id": 54 }, { "id": 47 }],
        [{ "id": 39 }, { "id": 46 }, { "id": 55 }],
        [{ "id": 40 }, { "id": 56 }, { "id": 49 }],
        [{ "id": 41 }, { "id": 48 }, { "id": 57 }, { "id": 50 }],
        [{ "id": 42 }, { "id": 49 }, { "id": 58 }, { "id": 51 }],
        [{ "id": 43 }, { "id": 50 }, { "id": 59 }, { "id": 52 }],
        [{ "id": 44 }, { "id": 51 }, { "id": 60 }, { "id": 53 }],
        [{ "id": 45 }, { "id": 52 }, { "id": 61 }, { "id": 54 }],
        [{ "id": 46 }, { "id": 53 }, { "id": 62 }, { "id": 55 }],
        [{ "id": 47 }, { "id": 54 }, { "id": 63 }],
        [{ "id": 48 }, { "id": 57 }],
        [{ "id": 49 }, { "id": 56 }, { "id": 58 }],
        [{ "id": 50 }, { "id": 57 }, { "id": 59 }],
        [{ "id": 51 }, { "id": 58 }, { "id": 60 }],
        [{ "id": 52 }, { "id": 59 }, { "id": 61 }],
        [{ "id": 53 }, { "id": 60 }, { "id": 62 }],
        [{ "id": 54 }, { "id": 61 }, { "id": 63 }],
        [{ "id": 55 }, { "id": 62 }]
    ]
}
